[
    {
        "tested": 163,
        "release": "1.5.0",
        "untested": 3,
        "total tested": 163,
        "new endpoints": 166,
        "total untested": 3,
        "total endpoints": 166
    },
    {
        "tested": 4,
        "release": "1.6.0",
        "untested": 2,
        "total tested": 167,
        "new endpoints": 6,
        "total untested": 5,
        "total endpoints": 172
    },
    {
        "tested": 8,
        "release": "1.7.0",
        "untested": 0,
        "total tested": 175,
        "new endpoints": 8,
        "total untested": 5,
        "total endpoints": 180
    },
    {
        "tested": 7,
        "release": "1.8.0",
        "untested": 0,
        "total tested": 182,
        "new endpoints": 7,
        "total untested": 5,
        "total endpoints": 187
    },
    {
        "tested": 62,
        "release": "1.9.0",
        "untested": 1,
        "total tested": 244,
        "new endpoints": 63,
        "total untested": 6,
        "total endpoints": 250
    },
    {
        "tested": 8,
        "release": "1.10.0",
        "untested": 1,
        "total tested": 252,
        "new endpoints": 9,
        "total untested": 7,
        "total endpoints": 259
    },
    {
        "tested": 2,
        "release": "1.11.0",
        "untested": 0,
        "total tested": 254,
        "new endpoints": 2,
        "total untested": 7,
        "total endpoints": 261
    },
    {
        "tested": 1,
        "release": "1.12.0",
        "untested": 0,
        "total tested": 255,
        "new endpoints": 1,
        "total untested": 7,
        "total endpoints": 262
    },
    {
        "tested": 0,
        "release": "1.13.0",
        "untested": 0,
        "total tested": 255,
        "new endpoints": 0,
        "total untested": 7,
        "total endpoints": 262
    },
    {
        "tested": 16,
        "release": "1.14.0",
        "untested": 2,
        "total tested": 271,
        "new endpoints": 18,
        "total untested": 9,
        "total endpoints": 280
    },
    {
        "tested": 0,
        "release": "1.15.0",
        "untested": 0,
        "total tested": 271,
        "new endpoints": 0,
        "total untested": 9,
        "total endpoints": 280
    },
    {
        "tested": 27,
        "release": "1.16.0",
        "untested": 0,
        "total tested": 298,
        "new endpoints": 27,
        "total untested": 9,
        "total endpoints": 307
    },
    {
        "tested": 0,
        "release": "1.17.0",
        "untested": 0,
        "total tested": 298,
        "new endpoints": 0,
        "total untested": 9,
        "total endpoints": 307
    },
    {
        "tested": 4,
        "release": "1.18.0",
        "untested": 0,
        "total tested": 302,
        "new endpoints": 4,
        "total untested": 9,
        "total endpoints": 311
    },
    {
        "tested": 40,
        "release": "1.19.0",
        "untested": 1,
        "total tested": 342,
        "new endpoints": 41,
        "total untested": 10,
        "total endpoints": 352
    },
    {
        "tested": 8,
        "release": "1.20.0",
        "untested": 0,
        "total tested": 350,
        "new endpoints": 8,
        "total untested": 10,
        "total endpoints": 360
    },
    {
        "tested": 31,
        "release": "1.21.0",
        "untested": 1,
        "total tested": 381,
        "new endpoints": 32,
        "total untested": 11,
        "total endpoints": 392
    },
    {
        "tested": 0,
        "release": "1.22.0",
        "untested": 0,
        "total tested": 381,
        "new endpoints": 0,
        "total untested": 11,
        "total endpoints": 392
    },
    {
        "tested": 1,
        "release": "1.23.0",
        "untested": 1,
        "total tested": 382,
        "new endpoints": 2,
        "total untested": 12,
        "total endpoints": 394
    },
    {
        "tested": 8,
        "release": "1.24.0",
        "untested": 0,
        "total tested": 390,
        "new endpoints": 8,
        "total untested": 12,
        "total endpoints": 402
    },
    {
        "tested": 0,
        "release": "1.25.0",
        "untested": 0,
        "total tested": 390,
        "new endpoints": 0,
        "total untested": 12,
        "total endpoints": 402
    },
    {
        "tested": 0,
        "release": "1.26.0",
        "untested": 0,
        "total tested": 390,
        "new endpoints": 0,
        "total untested": 12,
        "total endpoints": 402
    },
    {
        "tested": 0,
        "release": "1.27.0",
        "untested": 0,
        "total tested": 390,
        "new endpoints": 0,
        "total untested": 12,
        "total endpoints": 402
    }
]
